cdn_proxy/__init__.py
cdn_proxy/__main__.py
cdn_proxy/cli.py
cdn_proxy/cloudflare/__init__.py
cdn_proxy/cloudflare/cli.py
cdn_proxy/cloudflare/main.py
cdn_proxy/cloudfront/__init__.py
cdn_proxy/cloudfront/cli.py
cdn_proxy/cloudfront/main.py
cdn_proxy/cloudfront/req_lambda/.gitignore
cdn_proxy/cloudfront/req_lambda/Dockerfile
cdn_proxy/cloudfront/req_lambda/Makefile
cdn_proxy/cloudfront/req_lambda/build/asset-manifest.json
cdn_proxy/cloudfront/req_lambda/build/index.html
cdn_proxy/cloudfront/req_lambda/build/static/css/main.b623609b.chunk.css
cdn_proxy/cloudfront/req_lambda/build/static/css/main.b623609b.chunk.css.map
cdn_proxy/cloudfront/req_lambda/build/static/js/2.41bacb38.chunk.js
cdn_proxy/cloudfront/req_lambda/build/static/js/2.41bacb38.chunk.js.LICENSE.txt
cdn_proxy/cloudfront/req_lambda/build/static/js/2.41bacb38.chunk.js.map
cdn_proxy/cloudfront/req_lambda/build/static/js/main.37e49def.chunk.js
cdn_proxy/cloudfront/req_lambda/build/static/js/main.37e49def.chunk.js.map
cdn_proxy/cloudfront/req_lambda/build/static/js/runtime-main.6b4523a0.js
cdn_proxy/cloudfront/req_lambda/build/static/js/runtime-main.6b4523a0.js.map
cdn_proxy/cloudfront/req_lambda/config-overrides.js
cdn_proxy/cloudfront/req_lambda/main.py
cdn_proxy/cloudfront/req_lambda/package.json
cdn_proxy/cloudfront/req_lambda/public/index.html
cdn_proxy/cloudfront/req_lambda/src/App.css
cdn_proxy/cloudfront/req_lambda/src/App.test.tsx
cdn_proxy/cloudfront/req_lambda/src/App.tsx
cdn_proxy/cloudfront/req_lambda/src/CloudFrontScanner.test.tsx
cdn_proxy/cloudfront/req_lambda/src/CloudFrontScanner.ts
cdn_proxy/cloudfront/req_lambda/src/Help.tsx
cdn_proxy/cloudfront/req_lambda/src/Scanner.tsx
cdn_proxy/cloudfront/req_lambda/src/index.css
cdn_proxy/cloudfront/req_lambda/src/index.tsx
cdn_proxy/cloudfront/req_lambda/src/react-app-env.d.ts
cdn_proxy/cloudfront/req_lambda/src/setupTests.ts
cdn_proxy/cloudfront/req_lambda/tsconfig.json
cdn_proxy/cloudfront/req_lambda/yarn-error.log
cdn_proxy-0.1.8.dist-info/entry_points.txt
cdn_proxy-0.1.8.dist-info/LICENSE
cdn_proxy-0.1.8.dist-info/WHEEL
cdn_proxy-0.1.8.dist-info/METADATA
cdn_proxy-0.1.8.dist-info/RECORD
