Metadata-Version: 2.1
Name: cdn-proxy
Version: 0.1.8
Summary: Take advantage of IP whitelisting of shared CDNs.
License: BSD-3
Author: Ryan Gerstenkorn
Requires-Python: >=3.6.2,<4.0.0
Classifier: License :: Other/Proprietary License
Classifier: Programming Language :: Python :: 3
Classifier: Programming Language :: Python :: 3.10
Classifier: Programming Language :: Python :: 3.7
Classifier: Programming Language :: Python :: 3.8
Classifier: Programming Language :: Python :: 3.9
Requires-Dist: boto3 (>=1.18.25,<2.0.0)
Requires-Dist: botocore (>=1.21.25,<2.0.0)
Requires-Dist: cloudflare (>=2.8.15,<3.0.0)
Requires-Dist: requests (>=2.26.0,<3.0.0)
Requires-Dist: typer (>=0.3.2,<0.4.0)
Requires-Dist: urllib3 (>=1.26.7,<2.0.0)
